README.rst
setup.py
PABBA/__init__.py
PABBA/agg.py
PABBA/aggmem.c
PABBA/aggmem.pyx
PABBA/comp.py
PABBA/compmem.c
PABBA/compmem.pyx
PABBA/fkmns.py
PABBA/inverset.py
PABBA/inversetc.c
PABBA/inversetc.pyx
PABBA/pabba.py
PABBA.egg-info/PKG-INFO
PABBA.egg-info/SOURCES.txt
PABBA.egg-info/dependency_links.txt
PABBA.egg-info/requires.txt
PABBA.egg-info/top_level.txt
PABBA/__pycache__/__init__.cpython-39.pyc
PABBA/__pycache__/agg.cpython-39.pyc
PABBA/__pycache__/comp.cpython-39.pyc
PABBA/__pycache__/fkmns.cpython-39.pyc
PABBA/__pycache__/inverset.cpython-39.pyc
PABBA/__pycache__/pabba.cpython-39.pyc
egg-info/PKG-INFO
egg-info/SOURCES.txt
egg-info/dependency_links.txt
egg-info/requires.txt
egg-info/top_level.txt